mycalc/calculator.py
jungwonhee-1.0.1.dist-info/LICENSE
jungwonhee-1.0.1.dist-info/METADATA
jungwonhee-1.0.1.dist-info/WHEEL
jungwonhee-1.0.1.dist-info/top_level.txt
jungwonhee-1.0.1.dist-info/RECORD
