Metadata-Version: 2.1
Name: jungwonhee
Version: 1.0.1
Summary: nice calc
Home-page: http://github.com/chunsejin/abc
Download-URL: http://github.com/chunsejin/abc/
Author: jungwonhee
License: UNKNOWN
Platform: UNKNOWN
Classifier: Programming Language :: Python :: 3
License-File: LICENSE
